{
  "timestamp": "2026-01-06T18:50:29.563770Z",
  "symbols": {
    "BTCUSDT": {
      "prices": {
        "Binance": 92130.87,
        "OKX": 92146.0,
        "KuCoin": 92141.4,
        "Gate": 92145.2,
        "MEXC": 92145.92
      },
      "absolute_diff": 15.13,
      "spread_percent": 0.00016422,
      "best_buy": {
        "exchange": "Binance",
        "price": 92130.87
      },
      "best_sell": {
        "exchange": "OKX",
        "price": 92146.0
      },
      "binance_price": 92130.87,
      "bybit_price": null
    },
    "ETHUSDT": {
      "prices": {
        "Binance": 3225.97,
        "OKX": 3225.7,
        "KuCoin": 3225.88,
        "Gate": 3225.49,
        "MEXC": 3226.63
      },
      "absolute_diff": 1.14,
      "spread_percent": 0.00035343,
      "best_buy": {
        "exchange": "Gate",
        "price": 3225.49
      },
      "best_sell": {
        "exchange": "MEXC",
        "price": 3226.63
      },
      "binance_price": 3225.97,
      "bybit_price": null
    },
    "SOLUSDT": {
      "prices": {
        "Binance": 137.74,
        "OKX": 137.74,
        "KuCoin": 137.75,
        "Gate": 137.74,
        "MEXC": 137.74
      },
      "absolute_diff": 0.01,
      "spread_percent": 7.26e-05,
      "best_buy": {
        "exchange": "Binance",
        "price": 137.74
      },
      "best_sell": {
        "exchange": "KuCoin",
        "price": 137.75
      },
      "binance_price": 137.74,
      "bybit_price": null
    },
    "XRPUSDT": {
      "prices": {
        "Binance": 2.2464,
        "OKX": 2.2473,
        "KuCoin": 2.24714,
        "Gate": 2.247,
        "MEXC": 2.2467
      },
      "absolute_diff": 0.0009,
      "spread_percent": 0.00040064,
      "best_buy": {
        "exchange": "Binance",
        "price": 2.2464
      },
      "best_sell": {
        "exchange": "OKX",
        "price": 2.2473
      },
      "binance_price": 2.2464,
      "bybit_price": null
    },
    "ADAUSDT": {
      "prices": {
        "Binance": 0.4082,
        "OKX": 0.4085,
        "KuCoin": 0.4082,
        "Gate": 0.4086,
        "MEXC": 0.4087
      },
      "absolute_diff": 0.0005,
      "spread_percent": 0.00122489,
      "best_buy": {
        "exchange": "Binance",
        "price": 0.4082
      },
      "best_sell": {
        "exchange": "MEXC",
        "price": 0.4087
      },
      "binance_price": 0.4082,
      "bybit_price": null
    },
    "DOGEUSDT": {
      "prices": {
        "Binance": 0.14581,
        "OKX": 0.14585,
        "KuCoin": 0.14595,
        "Gate": 0.14588,
        "MEXC": 0.14593
      },
      "absolute_diff": 0.00014,
      "spread_percent": 0.00096015,
      "best_buy": {
        "exchange": "Binance",
        "price": 0.14581
      },
      "best_sell": {
        "exchange": "KuCoin",
        "price": 0.14595
      },
      "binance_price": 0.14581,
      "bybit_price": null
    },
    "DOTUSDT": {
      "prices": {
        "Binance": 2.155,
        "OKX": 2.155,
        "KuCoin": 2.1555,
        "Gate": 2.157,
        "MEXC": 2.156
      },
      "absolute_diff": 0.002,
      "spread_percent": 0.00092807,
      "best_buy": {
        "exchange": "Binance",
        "price": 2.155
      },
      "best_sell": {
        "exchange": "Gate",
        "price": 2.157
      },
      "binance_price": 2.155,
      "bybit_price": null
    },
    "LINKUSDT": {
      "prices": {
        "Binance": 13.66,
        "OKX": 13.663,
        "KuCoin": 13.6604,
        "Gate": 13.661,
        "MEXC": 13.66
      },
      "absolute_diff": 0.003,
      "spread_percent": 0.00021962,
      "best_buy": {
        "exchange": "Binance",
        "price": 13.66
      },
      "best_sell": {
        "exchange": "OKX",
        "price": 13.663
      },
      "binance_price": 13.66,
      "bybit_price": null
    },
    "MATICUSDT": {
      "prices": {
        "Binance": 0.3794
      },
      "absolute_diff": null,
      "spread_percent": null,
      "best_buy": null,
      "best_sell": null,
      "binance_price": 0.3794,
      "bybit_price": null
    }
  },
  "errors": {
    "BTCUSDT": {
      "Bybit": "HTTP 403 Forbidden"
    },
    "ETHUSDT": {
      "Bybit": "HTTP 403 Forbidden"
    },
    "SOLUSDT": {
      "Bybit": "HTTP 403 Forbidden"
    },
    "XRPUSDT": {
      "Bybit": "HTTP 403 Forbidden"
    },
    "ADAUSDT": {
      "Bybit": "HTTP 403 Forbidden"
    },
    "DOGEUSDT": {
      "Bybit": "HTTP 403 Forbidden"
    },
    "DOTUSDT": {
      "Bybit": "HTTP 403 Forbidden"
    },
    "LINKUSDT": {
      "Bybit": "HTTP 403 Forbidden"
    },
    "MATICUSDT": {
      "OKX": "Empty data list",
      "KuCoin": "TypeError: 'NoneType' object is not subscriptable",
      "Gate": "HTTP 400 Bad Request",
      "MEXC": "HTTP 400 Bad Request",
      "Bybit": "HTTP 403 Forbidden"
    }
  },
  "exchanges": [
    "Binance",
    "OKX",
    "KuCoin",
    "Gate",
    "MEXC",
    "Bybit"
  ]
}