{
  "timestamp": "2026-04-06T03:44:03.813630+00:00",
  "symbols": {
    "BTCUSDT": {
      "prices": {
        "Binance": 69126.51,
        "MEXC": 69126.67,
        "OKX": 69127.9,
        "KuCoin": 69126.7,
        "Gate": 69124.0
      },
      "absolute_diff": 3.9,
      "spread_percent": 5.642e-05,
      "best_buy": {
        "exchange": "Gate",
        "price": 69124.0
      },
      "best_sell": {
        "exchange": "OKX",
        "price": 69127.9
      },
      "binance_price": 69126.51,
      "bybit_price": null
    },
    "ETHUSDT": {
      "prices": {
        "Binance": 2131.82,
        "MEXC": 2131.94,
        "OKX": 2131.76,
        "KuCoin": 2131.21,
        "Gate": 2131.88
      },
      "absolute_diff": 0.73,
      "spread_percent": 0.00034253,
      "best_buy": {
        "exchange": "KuCoin",
        "price": 2131.21
      },
      "best_sell": {
        "exchange": "MEXC",
        "price": 2131.94
      },
      "binance_price": 2131.82,
      "bybit_price": null
    },
    "SOLUSDT": {
      "prices": {
        "Binance": 82.01,
        "MEXC": 82.0,
        "OKX": 82.02,
        "KuCoin": 82.0,
        "Gate": 82.02
      },
      "absolute_diff": 0.02,
      "spread_percent": 0.0002439,
      "best_buy": {
        "exchange": "MEXC",
        "price": 82.0
      },
      "best_sell": {
        "exchange": "OKX",
        "price": 82.02
      },
      "binance_price": 82.01,
      "bybit_price": null
    },
    "XRPUSDT": {
      "prices": {
        "Binance": 1.3381,
        "MEXC": 1.3379,
        "OKX": 1.3381,
        "KuCoin": 1.33801,
        "Gate": 1.338
      },
      "absolute_diff": 0.0,
      "spread_percent": 0.00014949,
      "best_buy": {
        "exchange": "MEXC",
        "price": 1.3379
      },
      "best_sell": {
        "exchange": "Binance",
        "price": 1.3381
      },
      "binance_price": 1.3381,
      "bybit_price": null
    },
    "TONUSDT": {
      "prices": {
        "Binance": 1.253,
        "MEXC": 1.254,
        "OKX": 1.253,
        "KuCoin": 1.2537,
        "Gate": 1.2538
      },
      "absolute_diff": 0.0,
      "spread_percent": 0.00079808,
      "best_buy": {
        "exchange": "Binance",
        "price": 1.253
      },
      "best_sell": {
        "exchange": "MEXC",
        "price": 1.254
      },
      "binance_price": 1.253,
      "bybit_price": null
    },
    "DOGEUSDT": {
      "prices": {
        "Binance": 0.09248,
        "MEXC": 0.09249,
        "OKX": 0.09248,
        "KuCoin": 0.09248,
        "Gate": 0.0925
      },
      "absolute_diff": 0.0,
      "spread_percent": 0.00021626,
      "best_buy": {
        "exchange": "Binance",
        "price": 0.09248
      },
      "best_sell": {
        "exchange": "Gate",
        "price": 0.0925
      },
      "binance_price": 0.09248,
      "bybit_price": null
    },
    "ADAUSDT": {
      "prices": {
        "Binance": 0.2569,
        "MEXC": 0.2569,
        "OKX": 0.2569,
        "KuCoin": 0.2568,
        "Gate": 0.2567
      },
      "absolute_diff": 0.0,
      "spread_percent": 0.00077912,
      "best_buy": {
        "exchange": "Gate",
        "price": 0.2567
      },
      "best_sell": {
        "exchange": "Binance",
        "price": 0.2569
      },
      "binance_price": 0.2569,
      "bybit_price": null
    },
    "BNBUSDT": {
      "prices": {
        "Binance": 600.92,
        "MEXC": 600.97,
        "OKX": 601.1,
        "KuCoin": 600.747,
        "Gate": 600.9
      },
      "absolute_diff": 0.35,
      "spread_percent": 0.0005876,
      "best_buy": {
        "exchange": "KuCoin",
        "price": 600.747
      },
      "best_sell": {
        "exchange": "OKX",
        "price": 601.1
      },
      "binance_price": 600.92,
      "bybit_price": null
    },
    "TRXUSDT": {
      "prices": {
        "Binance": 0.3186,
        "MEXC": 0.3186,
        "OKX": 0.31853,
        "KuCoin": 0.3184,
        "Gate": 0.31848
      },
      "absolute_diff": 0.0,
      "spread_percent": 0.00062814,
      "best_buy": {
        "exchange": "KuCoin",
        "price": 0.3184
      },
      "best_sell": {
        "exchange": "Binance",
        "price": 0.3186
      },
      "binance_price": 0.3186,
      "bybit_price": null
    },
    "DOTUSDT": {
      "prices": {
        "Binance": 1.261,
        "MEXC": 1.26,
        "OKX": 1.261,
        "KuCoin": 1.261,
        "Gate": 1.261
      },
      "absolute_diff": 0.0,
      "spread_percent": 0.00079365,
      "best_buy": {
        "exchange": "MEXC",
        "price": 1.26
      },
      "best_sell": {
        "exchange": "Binance",
        "price": 1.261
      },
      "binance_price": 1.261,
      "bybit_price": null
    },
    "LINKUSDT": {
      "prices": {
        "Binance": 8.95,
        "MEXC": 8.944,
        "OKX": 8.946,
        "KuCoin": 8.9448,
        "Gate": 8.945
      },
      "absolute_diff": 0.01,
      "spread_percent": 0.00067084,
      "best_buy": {
        "exchange": "MEXC",
        "price": 8.944
      },
      "best_sell": {
        "exchange": "Binance",
        "price": 8.95
      },
      "binance_price": 8.95,
      "bybit_price": null
    },
    "LTCUSDT": {
      "prices": {
        "Binance": 54.34,
        "MEXC": 54.31,
        "OKX": 54.32,
        "KuCoin": 54.33,
        "Gate": 54.29
      },
      "absolute_diff": 0.05,
      "spread_percent": 0.00092098,
      "best_buy": {
        "exchange": "Gate",
        "price": 54.29
      },
      "best_sell": {
        "exchange": "Binance",
        "price": 54.34
      },
      "binance_price": 54.34,
      "bybit_price": null
    },
    "AVAXUSDT": {
      "prices": {
        "Binance": 9.5,
        "MEXC": 9.509,
        "OKX": 9.51,
        "KuCoin": 9.512,
        "Gate": 9.517
      },
      "absolute_diff": 0.02,
      "spread_percent": 0.00178947,
      "best_buy": {
        "exchange": "Binance",
        "price": 9.5
      },
      "best_sell": {
        "exchange": "Gate",
        "price": 9.517
      },
      "binance_price": 9.5,
      "bybit_price": null
    },
    "MATICUSDT": {
      "prices": {
        "Binance": 0.3794
      },
      "absolute_diff": 0.0,
      "spread_percent": 0.0,
      "best_buy": {
        "exchange": "Binance",
        "price": 0.3794
      },
      "best_sell": {
        "exchange": "Binance",
        "price": 0.3794
      },
      "binance_price": 0.3794,
      "bybit_price": null
    },
    "SHIBUSDT": {
      "prices": {
        "Binance": 6.02e-06,
        "MEXC": 6.015e-06,
        "OKX": 6.012e-06,
        "KuCoin": 6.013e-06,
        "Gate": 6.008e-06
      },
      "absolute_diff": 0.0,
      "spread_percent": 0.00199734,
      "best_buy": {
        "exchange": "Gate",
        "price": 6.008e-06
      },
      "best_sell": {
        "exchange": "Binance",
        "price": 6.02e-06
      },
      "binance_price": 6.02e-06,
      "bybit_price": null
    },
    "UNIUSDT": {
      "prices": {
        "Binance": 3.168,
        "MEXC": 3.168,
        "OKX": 3.17,
        "KuCoin": 3.1644,
        "Gate": 3.167
      },
      "absolute_diff": 0.01,
      "spread_percent": 0.00176969,
      "best_buy": {
        "exchange": "KuCoin",
        "price": 3.1644
      },
      "best_sell": {
        "exchange": "OKX",
        "price": 3.17
      },
      "binance_price": 3.168,
      "bybit_price": null
    },
    "XLMUSDT": {
      "prices": {
        "Binance": 0.162,
        "MEXC": 0.1619,
        "OKX": 0.162,
        "KuCoin": 0.162,
        "Gate": 0.16197
      },
      "absolute_diff": 0.0,
      "spread_percent": 0.00061767,
      "best_buy": {
        "exchange": "MEXC",
        "price": 0.1619
      },
      "best_sell": {
        "exchange": "Binance",
        "price": 0.162
      },
      "binance_price": 0.162,
      "bybit_price": null
    },
    "NEARUSDT": {
      "prices": {
        "Binance": 1.274,
        "MEXC": 1.2731,
        "OKX": 1.273,
        "KuCoin": 1.2735,
        "Gate": 1.2741
      },
      "absolute_diff": 0.0,
      "spread_percent": 0.0008641,
      "best_buy": {
        "exchange": "OKX",
        "price": 1.273
      },
      "best_sell": {
        "exchange": "Gate",
        "price": 1.2741
      },
      "binance_price": 1.274,
      "bybit_price": null
    },
    "ATOMUSDT": {
      "prices": {
        "Binance": 1.704,
        "MEXC": 1.705,
        "OKX": 1.704,
        "KuCoin": 1.7048,
        "Gate": 1.704
      },
      "absolute_diff": 0.0,
      "spread_percent": 0.00058685,
      "best_buy": {
        "exchange": "Binance",
        "price": 1.704
      },
      "best_sell": {
        "exchange": "MEXC",
        "price": 1.705
      },
      "binance_price": 1.704,
      "bybit_price": null
    },
    "APTUSDT": {
      "prices": {
        "Binance": 0.853,
        "MEXC": 0.8532,
        "OKX": 0.8528,
        "KuCoin": 0.8533,
        "Gate": 0.8514
      },
      "absolute_diff": 0.0,
      "spread_percent": 0.00223162,
      "best_buy": {
        "exchange": "Gate",
        "price": 0.8514
      },
      "best_sell": {
        "exchange": "KuCoin",
        "price": 0.8533
      },
      "binance_price": 0.853,
      "bybit_price": null
    }
  },
  "errors": {
    "MATICUSDT": {
      "MEXC": "HTTP 400 Bad Request",
      "OKX": "Empty data list",
      "KuCoin": "TypeError: 'NoneType' object is not subscriptable",
      "Gate": "HTTP 400 Bad Request"
    }
  },
  "exchanges": [
    "Binance",
    "MEXC",
    "OKX",
    "KuCoin",
    "Gate"
  ],
  "reachable_exchanges": [
    "Binance",
    "MEXC",
    "OKX",
    "KuCoin",
    "Gate"
  ]
}