{
  "timestamp": "2026-01-20T08:55:51.865370Z",
  "source": "gamma-api.polymarket.com",
  "markets": [
    {
      "id": "527079",
      "slug": "will-gta-6-cost-100",
      "question": "Will GTA 6 cost $100+?",
      "url": "https://polymarket.com/event/will-gta-6-cost-100",
      "image": "https://polymarket-upload.s3.us-east-2.amazonaws.com/gta-6-launch-price-l4GiOIOGhdvA.jpg",
      "endDate": "2026-02-28T12:00:00Z",
      "volume24hr": 63782.73036599999,
      "volume": 1476141.637483,
      "liquidity": 51928.16087,
      "yes": 0.019,
      "no": 0.981,
      "oneDayPriceChange": 0.0025,
      "outcomes": [
        {
          "name": "Yes",
          "price": 0.019
        },
        {
          "name": "No",
          "price": 0.981
        }
      ]
    },
    {
      "id": "537486",
      "slug": "will-the-us-collect-between-200b-and-500b-in-revenue-in-2025",
      "question": "Will the U.S. collect between $200b and $500b in revenue in 2025?",
      "url": "https://polymarket.com/event/will-the-us-collect-between-200b-and-500b-in-revenue-in-2025",
      "image": "https://polymarket-upload.s3.us-east-2.amazonaws.com/how-much-revenue-will-the-us-raise-from-tariffs-in-2025-lUbEhM1AK-xa.jpg",
      "endDate": "2026-02-28T12:00:00Z",
      "volume24hr": 22939.000593000008,
      "volume": 470549.347524,
      "liquidity": 9083.986,
      "yes": 0.185,
      "no": 0.815,
      "oneDayPriceChange": -0.075,
      "outcomes": [
        {
          "name": "Yes",
          "price": 0.185
        },
        {
          "name": "No",
          "price": 0.815
        }
      ]
    },
    {
      "id": "537487",
      "slug": "will-the-us-collect-between-500b-and-1t-in-revenue-in-2025",
      "question": "Will the U.S. collect between $500b and $1t in revenue in 2025?",
      "url": "https://polymarket.com/event/will-the-us-collect-between-500b-and-1t-in-revenue-in-2025",
      "image": "https://polymarket-upload.s3.us-east-2.amazonaws.com/how-much-revenue-will-the-us-raise-from-tariffs-in-2025-lUbEhM1AK-xa.jpg",
      "endDate": "2026-02-28T12:00:00Z",
      "volume24hr": 13527.113973000001,
      "volume": 334839.586113,
      "liquidity": 8923.68659,
      "yes": 0.018,
      "no": 0.982,
      "oneDayPriceChange": 0.015,
      "outcomes": [
        {
          "name": "Yes",
          "price": 0.018
        },
        {
          "name": "No",
          "price": 0.982
        }
      ]
    },
    {
      "id": "537485",
      "slug": "will-the-us-collect-between-100b-and-200b-in-revenue-in-2025",
      "question": "Will the U.S. collect between $100b and $200b in revenue in 2025?",
      "url": "https://polymarket.com/event/will-the-us-collect-between-100b-and-200b-in-revenue-in-2025",
      "image": "https://polymarket-upload.s3.us-east-2.amazonaws.com/how-much-revenue-will-the-us-raise-from-tariffs-in-2025-lUbEhM1AK-xa.jpg",
      "endDate": "2026-02-28T12:00:00Z",
      "volume24hr": 12545.238074999985,
      "volume": 794416.070818,
      "liquidity": 11098.5854,
      "yes": 0.17,
      "no": 0.83,
      "oneDayPriceChange": 0.005,
      "outcomes": [
        {
          "name": "Yes",
          "price": 0.17
        },
        {
          "name": "No",
          "price": 0.83
        }
      ]
    },
    {
      "id": "537484",
      "slug": "will-the-us-collect-less-than-100b-in-revenue-in-2025",
      "question": "Will the U.S. collect less than $100b in revenue in 2025?",
      "url": "https://polymarket.com/event/will-the-us-collect-less-than-100b-in-revenue-in-2025",
      "image": "https://polymarket-upload.s3.us-east-2.amazonaws.com/how-much-revenue-will-the-us-raise-from-tariffs-in-2025-lUbEhM1AK-xa.jpg",
      "endDate": "2026-02-28T12:00:00Z",
      "volume24hr": 10241.295211999999,
      "volume": 782466.362152,
      "liquidity": 23752.62064,
      "yes": 0.5635,
      "no": 0.4365,
      "oneDayPriceChange": -0.02,
      "outcomes": [
        {
          "name": "Yes",
          "price": 0.5635
        },
        {
          "name": "No",
          "price": 0.4365
        }
      ]
    },
    {
      "id": "537488",
      "slug": "will-the-us-collect-between-1t-and-2t-in-revenue-in-2025",
      "question": "Will the U.S. collect between $1t and $2t in revenue in 2025?",
      "url": "https://polymarket.com/event/will-the-us-collect-between-1t-and-2t-in-revenue-in-2025",
      "image": "https://polymarket-upload.s3.us-east-2.amazonaws.com/how-much-revenue-will-the-us-raise-from-tariffs-in-2025-lUbEhM1AK-xa.jpg",
      "endDate": "2026-02-28T12:00:00Z",
      "volume24hr": 8727.36,
      "volume": 241056.40223,
      "liquidity": 24619.50249,
      "yes": 0.003,
      "no": 0.997,
      "oneDayPriceChange": 0.0025,
      "outcomes": [
        {
          "name": "Yes",
          "price": 0.003
        },
        {
          "name": "No",
          "price": 0.997
        }
      ]
    },
    {
      "id": "521963",
      "slug": "will-elon-cut-the-budget-by-at-least-10-in-2025",
      "question": "Will Elon cut the budget by at least 10% in 2025?",
      "url": "https://polymarket.com/event/will-elon-cut-the-budget-by-at-least-10-in-2025",
      "image": "https://polymarket-upload.s3.us-east-2.amazonaws.com/will-elon-cut-the-budget-by-at-least-10-in-2025-KQWXFwQwSRYV.jpg",
      "endDate": "2026-02-28T12:00:00Z",
      "volume24hr": 6911.739203000001,
      "volume": 124546.13135,
      "liquidity": 14827.85815,
      "yes": 0.0115,
      "no": 0.9885,
      "oneDayPriceChange": 0.001,
      "outcomes": [
        {
          "name": "Yes",
          "price": 0.0115
        },
        {
          "name": "No",
          "price": 0.9885
        }
      ]
    },
    {
      "id": "537489",
      "slug": "will-the-us-collect-more-than-2t-in-revenue-in-2025",
      "question": "Will the U.S. collect more than $2t in revenue in 2025?",
      "url": "https://polymarket.com/event/will-the-us-collect-more-than-2t-in-revenue-in-2025",
      "image": "https://polymarket-upload.s3.us-east-2.amazonaws.com/how-much-revenue-will-the-us-raise-from-tariffs-in-2025-lUbEhM1AK-xa.jpg",
      "endDate": "2026-02-28T12:00:00Z",
      "volume24hr": 3996.2836649999995,
      "volume": 200986.059574,
      "liquidity": 28825.46291,
      "yes": 0.0045,
      "no": 0.9955,
      "oneDayPriceChange": 0.0005,
      "outcomes": [
        {
          "name": "Yes",
          "price": 0.0045
        },
        {
          "name": "No",
          "price": 0.9955
        }
      ]
    },
    {
      "id": "517321",
      "slug": "will-trump-deport-750000-or-more-people-in-2025",
      "question": "Will Trump deport 750,000 or more people in 2025?",
      "url": "https://polymarket.com/event/will-trump-deport-750000-or-more-people-in-2025",
      "image": "https://polymarket-upload.s3.us-east-2.amazonaws.com/will-trump-deport-750000-or-more-people-in-2025-xhG2x_HIG7ZG.jpg",
      "endDate": "2025-12-31T12:00:00Z",
      "volume24hr": 3767.230658999999,
      "volume": 406808.477476,
      "liquidity": 1621.04827,
      "yes": 0.0525,
      "no": 0.9475,
      "oneDayPriceChange": 0.0305,
      "outcomes": [
        {
          "name": "Yes",
          "price": 0.0525
        },
        {
          "name": "No",
          "price": 0.9475
        }
      ]
    },
    {
      "id": "517317",
      "slug": "will-trump-deport-1500000-1750000-people",
      "question": "Will Trump deport 1,500,000-1,750,000 people?",
      "url": "https://polymarket.com/event/will-trump-deport-1500000-1750000-people",
      "image": "https://polymarket-upload.s3.us-east-2.amazonaws.com/how-many-people-will-trump-deport-in-2025-itZ0rMnIYuju.jpg",
      "endDate": "2025-12-31T12:00:00Z",
      "volume24hr": 3510.1655000000005,
      "volume": 358421.797316,
      "liquidity": 10968.58074,
      "yes": 0.0055,
      "no": 0.9945,
      "oneDayPriceChange": 0.003,
      "outcomes": [
        {
          "name": "Yes",
          "price": 0.0055
        },
        {
          "name": "No",
          "price": 0.9945
        }
      ]
    },
    {
      "id": "517316",
      "slug": "will-trump-deport-1250000-1500000-people",
      "question": "Will Trump deport 1,250,000-1,500,000 people?",
      "url": "https://polymarket.com/event/will-trump-deport-1250000-1500000-people",
      "image": "https://polymarket-upload.s3.us-east-2.amazonaws.com/how-many-people-will-trump-deport-in-2025-itZ0rMnIYuju.jpg",
      "endDate": "2025-12-31T12:00:00Z",
      "volume24hr": 2139.748555,
      "volume": 327277.665249,
      "liquidity": 10260.03276,
      "yes": 0.0055,
      "no": 0.9945,
      "oneDayPriceChange": 0.003,
      "outcomes": [
        {
          "name": "Yes",
          "price": 0.0055
        },
        {
          "name": "No",
          "price": 0.9945
        }
      ]
    },
    {
      "id": "517311",
      "slug": "will-trump-deport-250000-500000-people",
      "question": "Will Trump deport 250,000-500,000 people?",
      "url": "https://polymarket.com/event/will-trump-deport-250000-500000-people",
      "image": "https://polymarket-upload.s3.us-east-2.amazonaws.com/how-many-people-will-trump-deport-in-2025-itZ0rMnIYuju.jpg",
      "endDate": "2025-12-31T12:00:00Z",
      "volume24hr": 2013.697252,
      "volume": 1051658.805072,
      "liquidity": 10159.28998,
      "yes": 0.8735,
      "no": 0.1265,
      "oneDayPriceChange": 0.0135,
      "outcomes": [
        {
          "name": "Yes",
          "price": 0.8735
        },
        {
          "name": "No",
          "price": 0.1265
        }
      ]
    }
  ],
  "error": null
}