{
  "timestamp": "2026-04-16T09:51:53.607104+00:00",
  "symbols": {
    "BTCUSDT": {
      "prices": {
        "Binance": 74611.58,
        "MEXC": 74614.63,
        "OKX": 74615.8,
        "KuCoin": 74615.9,
        "Gate": 74611.6
      },
      "absolute_diff": 4.32,
      "spread_percent": 5.79e-05,
      "best_buy": {
        "exchange": "Binance",
        "price": 74611.58
      },
      "best_sell": {
        "exchange": "KuCoin",
        "price": 74615.9
      },
      "binance_price": 74611.58,
      "bybit_price": null
    },
    "ETHUSDT": {
      "prices": {
        "Binance": 2338.35,
        "MEXC": 2338.48,
        "OKX": 2338.53,
        "KuCoin": 2338.49,
        "Gate": 2338.39
      },
      "absolute_diff": 0.18,
      "spread_percent": 7.698e-05,
      "best_buy": {
        "exchange": "Binance",
        "price": 2338.35
      },
      "best_sell": {
        "exchange": "OKX",
        "price": 2338.53
      },
      "binance_price": 2338.35,
      "bybit_price": null
    },
    "SOLUSDT": {
      "prices": {
        "Binance": 85.26,
        "MEXC": 85.24,
        "OKX": 85.25,
        "KuCoin": 85.26,
        "Gate": 85.25
      },
      "absolute_diff": 0.02,
      "spread_percent": 0.00023463,
      "best_buy": {
        "exchange": "MEXC",
        "price": 85.24
      },
      "best_sell": {
        "exchange": "Binance",
        "price": 85.26
      },
      "binance_price": 85.26,
      "bybit_price": null
    },
    "XRPUSDT": {
      "prices": {
        "Binance": 1.4181,
        "MEXC": 1.4179,
        "OKX": 1.4183,
        "KuCoin": 1.41817,
        "Gate": 1.417
      },
      "absolute_diff": 0.0,
      "spread_percent": 0.00091743,
      "best_buy": {
        "exchange": "Gate",
        "price": 1.417
      },
      "best_sell": {
        "exchange": "OKX",
        "price": 1.4183
      },
      "binance_price": 1.4181,
      "bybit_price": null
    },
    "TONUSDT": {
      "prices": {
        "Binance": 1.411,
        "MEXC": 1.412,
        "OKX": 1.411,
        "KuCoin": 1.4115,
        "Gate": 1.412
      },
      "absolute_diff": 0.0,
      "spread_percent": 0.00070872,
      "best_buy": {
        "exchange": "Binance",
        "price": 1.411
      },
      "best_sell": {
        "exchange": "MEXC",
        "price": 1.412
      },
      "binance_price": 1.411,
      "bybit_price": null
    },
    "DOGEUSDT": {
      "prices": {
        "Binance": 0.09609,
        "MEXC": 0.0961,
        "OKX": 0.09608,
        "KuCoin": 0.09608,
        "Gate": 0.0961
      },
      "absolute_diff": 0.0,
      "spread_percent": 0.00020816,
      "best_buy": {
        "exchange": "OKX",
        "price": 0.09608
      },
      "best_sell": {
        "exchange": "MEXC",
        "price": 0.0961
      },
      "binance_price": 0.09609,
      "bybit_price": null
    },
    "ADAUSDT": {
      "prices": {
        "Binance": 0.2494,
        "MEXC": 0.2495,
        "OKX": 0.2494,
        "KuCoin": 0.2493,
        "Gate": 0.2493
      },
      "absolute_diff": 0.0,
      "spread_percent": 0.00080225,
      "best_buy": {
        "exchange": "KuCoin",
        "price": 0.2493
      },
      "best_sell": {
        "exchange": "MEXC",
        "price": 0.2495
      },
      "binance_price": 0.2494,
      "bybit_price": null
    },
    "BNBUSDT": {
      "prices": {
        "Binance": 622.56,
        "MEXC": 622.52,
        "OKX": 622.6,
        "KuCoin": 622.511,
        "Gate": 622.5
      },
      "absolute_diff": 0.1,
      "spread_percent": 0.00016064,
      "best_buy": {
        "exchange": "Gate",
        "price": 622.5
      },
      "best_sell": {
        "exchange": "OKX",
        "price": 622.6
      },
      "binance_price": 622.56,
      "bybit_price": null
    },
    "TRXUSDT": {
      "prices": {
        "Binance": 0.326,
        "MEXC": 0.326,
        "OKX": 0.32592,
        "KuCoin": 0.326,
        "Gate": 0.32587
      },
      "absolute_diff": 0.0,
      "spread_percent": 0.00039893,
      "best_buy": {
        "exchange": "Gate",
        "price": 0.32587
      },
      "best_sell": {
        "exchange": "Binance",
        "price": 0.326
      },
      "binance_price": 0.326,
      "bybit_price": null
    },
    "DOTUSDT": {
      "prices": {
        "Binance": 1.272,
        "MEXC": 1.27,
        "OKX": 1.272,
        "KuCoin": 1.2719,
        "Gate": 1.272
      },
      "absolute_diff": 0.0,
      "spread_percent": 0.0015748,
      "best_buy": {
        "exchange": "MEXC",
        "price": 1.27
      },
      "best_sell": {
        "exchange": "Binance",
        "price": 1.272
      },
      "binance_price": 1.272,
      "bybit_price": null
    },
    "LINKUSDT": {
      "prices": {
        "Binance": 9.28,
        "MEXC": 9.27,
        "OKX": 9.272,
        "KuCoin": 9.2706,
        "Gate": 9.271
      },
      "absolute_diff": 0.01,
      "spread_percent": 0.00107875,
      "best_buy": {
        "exchange": "MEXC",
        "price": 9.27
      },
      "best_sell": {
        "exchange": "Binance",
        "price": 9.28
      },
      "binance_price": 9.28,
      "bybit_price": null
    },
    "LTCUSDT": {
      "prices": {
        "Binance": 55.4,
        "MEXC": 55.43,
        "OKX": 55.41,
        "KuCoin": 55.41,
        "Gate": 55.39
      },
      "absolute_diff": 0.04,
      "spread_percent": 0.00072215,
      "best_buy": {
        "exchange": "Gate",
        "price": 55.39
      },
      "best_sell": {
        "exchange": "MEXC",
        "price": 55.43
      },
      "binance_price": 55.4,
      "bybit_price": null
    },
    "AVAXUSDT": {
      "prices": {
        "Binance": 9.44,
        "MEXC": 9.443,
        "OKX": 9.444,
        "KuCoin": 9.441,
        "Gate": 9.444
      },
      "absolute_diff": 0.0,
      "spread_percent": 0.00042373,
      "best_buy": {
        "exchange": "Binance",
        "price": 9.44
      },
      "best_sell": {
        "exchange": "OKX",
        "price": 9.444
      },
      "binance_price": 9.44,
      "bybit_price": null
    },
    "MATICUSDT": {
      "prices": {
        "Binance": 0.3794
      },
      "absolute_diff": 0.0,
      "spread_percent": 0.0,
      "best_buy": {
        "exchange": "Binance",
        "price": 0.3794
      },
      "best_sell": {
        "exchange": "Binance",
        "price": 0.3794
      },
      "binance_price": 0.3794,
      "bybit_price": null
    },
    "SHIBUSDT": {
      "prices": {
        "Binance": 6.06e-06,
        "MEXC": 6.058e-06,
        "OKX": 6.062e-06,
        "KuCoin": 6.059e-06,
        "Gate": 6.06e-06
      },
      "absolute_diff": 0.0,
      "spread_percent": 0.00066028,
      "best_buy": {
        "exchange": "MEXC",
        "price": 6.058e-06
      },
      "best_sell": {
        "exchange": "OKX",
        "price": 6.062e-06
      },
      "binance_price": 6.06e-06,
      "bybit_price": null
    },
    "UNIUSDT": {
      "prices": {
        "Binance": 3.265,
        "MEXC": 3.266,
        "OKX": 3.267,
        "KuCoin": 3.2663,
        "Gate": 3.264
      },
      "absolute_diff": 0.0,
      "spread_percent": 0.00091912,
      "best_buy": {
        "exchange": "Gate",
        "price": 3.264
      },
      "best_sell": {
        "exchange": "OKX",
        "price": 3.267
      },
      "binance_price": 3.265,
      "bybit_price": null
    },
    "XLMUSDT": {
      "prices": {
        "Binance": 0.1614,
        "MEXC": 0.1612,
        "OKX": 0.16122,
        "KuCoin": 0.1612,
        "Gate": 0.16128
      },
      "absolute_diff": 0.0,
      "spread_percent": 0.00124069,
      "best_buy": {
        "exchange": "MEXC",
        "price": 0.1612
      },
      "best_sell": {
        "exchange": "Binance",
        "price": 0.1614
      },
      "binance_price": 0.1614,
      "bybit_price": null
    },
    "NEARUSDT": {
      "prices": {
        "Binance": 1.405,
        "MEXC": 1.4051,
        "OKX": 1.404,
        "KuCoin": 1.4047,
        "Gate": 1.4047
      },
      "absolute_diff": 0.0,
      "spread_percent": 0.00078348,
      "best_buy": {
        "exchange": "OKX",
        "price": 1.404
      },
      "best_sell": {
        "exchange": "MEXC",
        "price": 1.4051
      },
      "binance_price": 1.405,
      "bybit_price": null
    },
    "ATOMUSDT": {
      "prices": {
        "Binance": 1.795,
        "MEXC": 1.795,
        "OKX": 1.796,
        "KuCoin": 1.7944,
        "Gate": 1.794
      },
      "absolute_diff": 0.0,
      "spread_percent": 0.00111483,
      "best_buy": {
        "exchange": "Gate",
        "price": 1.794
      },
      "best_sell": {
        "exchange": "OKX",
        "price": 1.796
      },
      "binance_price": 1.795,
      "bybit_price": null
    },
    "APTUSDT": {
      "prices": {
        "Binance": 0.926,
        "MEXC": 0.9271,
        "OKX": 0.9266,
        "KuCoin": 0.9258,
        "Gate": 0.9268
      },
      "absolute_diff": 0.0,
      "spread_percent": 0.00140419,
      "best_buy": {
        "exchange": "KuCoin",
        "price": 0.9258
      },
      "best_sell": {
        "exchange": "MEXC",
        "price": 0.9271
      },
      "binance_price": 0.926,
      "bybit_price": null
    }
  },
  "errors": {
    "MATICUSDT": {
      "MEXC": "HTTP 400 Bad Request",
      "OKX": "Empty data list",
      "KuCoin": "TypeError: 'NoneType' object is not subscriptable",
      "Gate": "HTTP 400 Bad Request"
    }
  },
  "exchanges": [
    "Binance",
    "MEXC",
    "OKX",
    "KuCoin",
    "Gate"
  ],
  "reachable_exchanges": [
    "Binance",
    "MEXC",
    "OKX",
    "KuCoin",
    "Gate"
  ]
}