{
  "timestamp": "2026-05-03T09:51:12.487799+00:00",
  "symbols": {
    "BTCUSDT": {
      "prices": {
        "Binance": 78509.51,
        "MEXC": 78514.29,
        "OKX": 78509.6,
        "KuCoin": 78511.5,
        "Gate": 78512.5
      },
      "absolute_diff": 4.78,
      "spread_percent": 6.088e-05,
      "best_buy": {
        "exchange": "Binance",
        "price": 78509.51
      },
      "best_sell": {
        "exchange": "MEXC",
        "price": 78514.29
      },
      "binance_price": 78509.51,
      "bybit_price": null
    },
    "ETHUSDT": {
      "prices": {
        "Binance": 2316.32,
        "MEXC": 2316.06,
        "OKX": 2316.54,
        "KuCoin": 2316.21,
        "Gate": 2316.32
      },
      "absolute_diff": 0.48,
      "spread_percent": 0.00020725,
      "best_buy": {
        "exchange": "MEXC",
        "price": 2316.06
      },
      "best_sell": {
        "exchange": "OKX",
        "price": 2316.54
      },
      "binance_price": 2316.32,
      "bybit_price": null
    },
    "SOLUSDT": {
      "prices": {
        "Binance": 84.02,
        "MEXC": 84.04,
        "OKX": 84.01,
        "KuCoin": 84.0,
        "Gate": 84.01
      },
      "absolute_diff": 0.04,
      "spread_percent": 0.00047619,
      "best_buy": {
        "exchange": "KuCoin",
        "price": 84.0
      },
      "best_sell": {
        "exchange": "MEXC",
        "price": 84.04
      },
      "binance_price": 84.02,
      "bybit_price": null
    },
    "XRPUSDT": {
      "prices": {
        "Binance": 1.3896,
        "MEXC": 1.3896,
        "OKX": 1.3895,
        "KuCoin": 1.38947,
        "Gate": 1.39
      },
      "absolute_diff": 0.0,
      "spread_percent": 0.00038144,
      "best_buy": {
        "exchange": "KuCoin",
        "price": 1.38947
      },
      "best_sell": {
        "exchange": "Gate",
        "price": 1.39
      },
      "binance_price": 1.3896,
      "bybit_price": null
    },
    "TONUSDT": {
      "prices": {
        "Binance": 1.341,
        "MEXC": 1.34,
        "OKX": 1.342,
        "KuCoin": 1.3408,
        "Gate": 1.3409
      },
      "absolute_diff": 0.0,
      "spread_percent": 0.00149254,
      "best_buy": {
        "exchange": "MEXC",
        "price": 1.34
      },
      "best_sell": {
        "exchange": "OKX",
        "price": 1.342
      },
      "binance_price": 1.341,
      "bybit_price": null
    },
    "DOGEUSDT": {
      "prices": {
        "Binance": 0.10816,
        "MEXC": 0.10817,
        "OKX": 0.10817,
        "KuCoin": 0.10817,
        "Gate": 0.10818
      },
      "absolute_diff": 0.0,
      "spread_percent": 0.00018491,
      "best_buy": {
        "exchange": "Binance",
        "price": 0.10816
      },
      "best_sell": {
        "exchange": "Gate",
        "price": 0.10818
      },
      "binance_price": 0.10816,
      "bybit_price": null
    },
    "ADAUSDT": {
      "prices": {
        "Binance": 0.2492,
        "MEXC": 0.2492,
        "OKX": 0.2491,
        "KuCoin": 0.249,
        "Gate": 0.2492
      },
      "absolute_diff": 0.0,
      "spread_percent": 0.00080321,
      "best_buy": {
        "exchange": "KuCoin",
        "price": 0.249
      },
      "best_sell": {
        "exchange": "Binance",
        "price": 0.2492
      },
      "binance_price": 0.2492,
      "bybit_price": null
    },
    "BNBUSDT": {
      "prices": {
        "Binance": 618.66,
        "MEXC": 618.65,
        "OKX": 618.9,
        "KuCoin": 618.824,
        "Gate": 618.7
      },
      "absolute_diff": 0.25,
      "spread_percent": 0.00040411,
      "best_buy": {
        "exchange": "MEXC",
        "price": 618.65
      },
      "best_sell": {
        "exchange": "OKX",
        "price": 618.9
      },
      "binance_price": 618.66,
      "bybit_price": null
    },
    "TRXUSDT": {
      "prices": {
        "Binance": 0.3403,
        "MEXC": 0.3404,
        "OKX": 0.34028,
        "KuCoin": 0.3403,
        "Gate": 0.34048
      },
      "absolute_diff": 0.0,
      "spread_percent": 0.00058775,
      "best_buy": {
        "exchange": "OKX",
        "price": 0.34028
      },
      "best_sell": {
        "exchange": "Gate",
        "price": 0.34048
      },
      "binance_price": 0.3403,
      "bybit_price": null
    },
    "DOTUSDT": {
      "prices": {
        "Binance": 1.212,
        "MEXC": 1.211,
        "OKX": 1.212,
        "KuCoin": 1.2119,
        "Gate": 1.213
      },
      "absolute_diff": 0.0,
      "spread_percent": 0.00165153,
      "best_buy": {
        "exchange": "MEXC",
        "price": 1.211
      },
      "best_sell": {
        "exchange": "Gate",
        "price": 1.213
      },
      "binance_price": 1.212,
      "bybit_price": null
    },
    "LINKUSDT": {
      "prices": {
        "Binance": 9.15,
        "MEXC": 9.139,
        "OKX": 9.145,
        "KuCoin": 9.145,
        "Gate": 9.144
      },
      "absolute_diff": 0.01,
      "spread_percent": 0.00120363,
      "best_buy": {
        "exchange": "MEXC",
        "price": 9.139
      },
      "best_sell": {
        "exchange": "Binance",
        "price": 9.15
      },
      "binance_price": 9.15,
      "bybit_price": null
    },
    "LTCUSDT": {
      "prices": {
        "Binance": 55.08,
        "MEXC": 55.08,
        "OKX": 55.08,
        "KuCoin": 55.08,
        "Gate": 55.09
      },
      "absolute_diff": 0.01,
      "spread_percent": 0.00018155,
      "best_buy": {
        "exchange": "Binance",
        "price": 55.08
      },
      "best_sell": {
        "exchange": "Gate",
        "price": 55.09
      },
      "binance_price": 55.08,
      "bybit_price": null
    },
    "AVAXUSDT": {
      "prices": {
        "Binance": 9.06,
        "MEXC": 9.068,
        "OKX": 9.062,
        "KuCoin": 9.061,
        "Gate": 9.061
      },
      "absolute_diff": 0.01,
      "spread_percent": 0.000883,
      "best_buy": {
        "exchange": "Binance",
        "price": 9.06
      },
      "best_sell": {
        "exchange": "MEXC",
        "price": 9.068
      },
      "binance_price": 9.06,
      "bybit_price": null
    },
    "MATICUSDT": {
      "prices": {
        "Binance": 0.3794
      },
      "absolute_diff": 0.0,
      "spread_percent": 0.0,
      "best_buy": {
        "exchange": "Binance",
        "price": 0.3794
      },
      "best_sell": {
        "exchange": "Binance",
        "price": 0.3794
      },
      "binance_price": 0.3794,
      "bybit_price": null
    },
    "SHIBUSDT": {
      "prices": {
        "Binance": 6.23e-06,
        "MEXC": 6.225e-06,
        "OKX": 6.226e-06,
        "KuCoin": 6.225e-06,
        "Gate": 6.228e-06
      },
      "absolute_diff": 0.0,
      "spread_percent": 0.00080321,
      "best_buy": {
        "exchange": "MEXC",
        "price": 6.225e-06
      },
      "best_sell": {
        "exchange": "Binance",
        "price": 6.23e-06
      },
      "binance_price": 6.23e-06,
      "bybit_price": null
    },
    "UNIUSDT": {
      "prices": {
        "Binance": 3.235,
        "MEXC": 3.235,
        "OKX": 3.236,
        "KuCoin": 3.2355,
        "Gate": 3.236
      },
      "absolute_diff": 0.0,
      "spread_percent": 0.00030912,
      "best_buy": {
        "exchange": "Binance",
        "price": 3.235
      },
      "best_sell": {
        "exchange": "OKX",
        "price": 3.236
      },
      "binance_price": 3.235,
      "bybit_price": null
    },
    "XLMUSDT": {
      "prices": {
        "Binance": 0.1592,
        "MEXC": 0.1593,
        "OKX": 0.15941,
        "KuCoin": 0.1593,
        "Gate": 0.15941
      },
      "absolute_diff": 0.0,
      "spread_percent": 0.0013191,
      "best_buy": {
        "exchange": "Binance",
        "price": 0.1592
      },
      "best_sell": {
        "exchange": "OKX",
        "price": 0.15941
      },
      "binance_price": 0.1592,
      "bybit_price": null
    },
    "NEARUSDT": {
      "prices": {
        "Binance": 1.275,
        "MEXC": 1.2749,
        "OKX": 1.275,
        "KuCoin": 1.2743,
        "Gate": 1.2748
      },
      "absolute_diff": 0.0,
      "spread_percent": 0.00054932,
      "best_buy": {
        "exchange": "KuCoin",
        "price": 1.2743
      },
      "best_sell": {
        "exchange": "Binance",
        "price": 1.275
      },
      "binance_price": 1.275,
      "bybit_price": null
    },
    "ATOMUSDT": {
      "prices": {
        "Binance": 1.874,
        "MEXC": 1.875,
        "OKX": 1.875,
        "KuCoin": 1.8764,
        "Gate": 1.876
      },
      "absolute_diff": 0.0,
      "spread_percent": 0.00128068,
      "best_buy": {
        "exchange": "Binance",
        "price": 1.874
      },
      "best_sell": {
        "exchange": "KuCoin",
        "price": 1.8764
      },
      "binance_price": 1.874,
      "bybit_price": null
    },
    "APTUSDT": {
      "prices": {
        "Binance": 0.981,
        "MEXC": 0.9813,
        "OKX": 0.9816,
        "KuCoin": 0.9814,
        "Gate": 0.9817
      },
      "absolute_diff": 0.0,
      "spread_percent": 0.00071356,
      "best_buy": {
        "exchange": "Binance",
        "price": 0.981
      },
      "best_sell": {
        "exchange": "Gate",
        "price": 0.9817
      },
      "binance_price": 0.981,
      "bybit_price": null
    }
  },
  "errors": {
    "MATICUSDT": {
      "MEXC": "HTTP 400 Bad Request",
      "OKX": "Empty data list",
      "KuCoin": "TypeError: 'NoneType' object is not subscriptable",
      "Gate": "HTTP 400 Bad Request"
    }
  },
  "exchanges": [
    "Binance",
    "MEXC",
    "OKX",
    "KuCoin",
    "Gate"
  ],
  "reachable_exchanges": [
    "Binance",
    "MEXC",
    "OKX",
    "KuCoin",
    "Gate"
  ]
}